zope2instance
