Metadata-Version: 1.0
Name: zope2instance
Version: 1.1
Summary: zc.buildout recipe for Zope 2.12+ instances.
Home-page: http://www.simplistix.co.uk/software/zope/zope2instance
Author: Chris Withers
Author-email: chris@simplistix.co.uk
License: MIT
Platform: UNKNOWN
Classifier: Development Status :: 5 - Production/Stable
Classifier: License :: OSI Approved :: MIT License
